PycHuffman.cp37-win32.pyd
PycHuffman-1.1.0.dist-info/LICENSE
PycHuffman-1.1.0.dist-info/METADATA
PycHuffman-1.1.0.dist-info/WHEEL
PycHuffman-1.1.0.dist-info/top_level.txt
PycHuffman-1.1.0.dist-info/RECORD
