Metadata-Version: 2.1
Name: PycHuffman
Version: 1.1.0
Summary: compress or decompress with huffman
Home-page: https://github.com/john04047210/pyhuffman.git
Author: QiaoPeng
Author-email: john_04047210@163.com
License: MIT License
Project-URL: Source, https://github.com/john04047210/pyhuffman.git
Platform: UNKNOWN
Classifier: Natural Language :: English
Classifier: Programming Language :: C
Classifier: Programming Language :: Python :: 3
Classifier: License :: OSI Approved :: MIT License
Classifier: Operating System :: Microsoft :: Windows
